{
  "source": "https://rest.cosmos.directory/cosmoshub",
  "scrapedAt": "2025-11-01T05:33:56.804Z",
  "chartId": "unbonding_chart",
  "title": "Cosmoshub unbondings map",
  "data": [
    {
      "date": "2025-11-01",
      "timestamp": 1761955200000,
      "value": 804657,
      "amount": 804657
    },
    {
      "date": "2025-11-02",
      "timestamp": 1762041600000,
      "value": 431786,
      "amount": 431786
    },
    {
      "date": "2025-11-03",
      "timestamp": 1762128000000,
      "value": 649475,
      "amount": 649475
    },
    {
      "date": "2025-11-04",
      "timestamp": 1762214400000,
      "value": 681579,
      "amount": 681579
    },
    {
      "date": "2025-11-05",
      "timestamp": 1762300800000,
      "value": 360877,
      "amount": 360877
    },
    {
      "date": "2025-11-06",
      "timestamp": 1762387200000,
      "value": 629474,
      "amount": 629474
    },
    {
      "date": "2025-11-07",
      "timestamp": 1762473600000,
      "value": 560685,
      "amount": 560685
    },
    {
      "date": "2025-11-08",
      "timestamp": 1762560000000,
      "value": 575585,
      "amount": 575585
    },
    {
      "date": "2025-11-09",
      "timestamp": 1762646400000,
      "value": 199484,
      "amount": 199484
    },
    {
      "date": "2025-11-10",
      "timestamp": 1762732800000,
      "value": 499608,
      "amount": 499608
    },
    {
      "date": "2025-11-11",
      "timestamp": 1762819200000,
      "value": 548696,
      "amount": 548696
    },
    {
      "date": "2025-11-12",
      "timestamp": 1762905600000,
      "value": 221946,
      "amount": 221946
    },
    {
      "date": "2025-11-13",
      "timestamp": 1762992000000,
      "value": 306259,
      "amount": 306259
    },
    {
      "date": "2025-11-14",
      "timestamp": 1763078400000,
      "value": 583618,
      "amount": 583618
    },
    {
      "date": "2025-11-15",
      "timestamp": 1763164800000,
      "value": 245541,
      "amount": 245541
    },
    {
      "date": "2025-11-16",
      "timestamp": 1763251200000,
      "value": 252347,
      "amount": 252347
    },
    {
      "date": "2025-11-17",
      "timestamp": 1763337600000,
      "value": 408980,
      "amount": 408980
    },
    {
      "date": "2025-11-18",
      "timestamp": 1763424000000,
      "value": 939808,
      "amount": 939808
    },
    {
      "date": "2025-11-19",
      "timestamp": 1763510400000,
      "value": 3351461,
      "amount": 3351461
    },
    {
      "date": "2025-11-20",
      "timestamp": 1763596800000,
      "value": 2816986,
      "amount": 2816986
    },
    {
      "date": "2025-11-21",
      "timestamp": 1763683200000,
      "value": 490217,
      "amount": 490217
    },
    {
      "date": "2025-11-22",
      "timestamp": 1763769600000,
      "value": 69258,
      "amount": 69258
    }
  ],
  "rawData": {
    "summary": {
      "validatorCount": 592,
      "totalUnbondingEntries": 18992,
      "totalUnbondingAtom": 15628326.84,
      "errors": [
        "cosmosvaloper14qazscc80zgzx3m0m0aa30ths0p9hg8vdglqrc: All LCD providers failed for cosmos/staking/v1beta1/validators/cosmosvaloper14qazscc80zgzx3m0m0aa30ths0p9hg8vdglqrc/unbonding_delegations: cosmos.directory: Mintscan request failed (429 Too Many Requests) for /cosmoshub/cosmos/staking/v1beta1/validators/cosmosvaloper14qazscc80zgzx3m0m0aa30ths0p9hg8vdglqrc/unbonding_delegations: ",
        "cosmosvaloper14jlpmqquh0gste6nzf4dn43kc8h50l6fmx6dfs: All LCD providers failed for cosmos/staking/v1beta1/validators/cosmosvaloper14jlpmqquh0gste6nzf4dn43kc8h50l6fmx6dfs/unbonding_delegations: cosmos.directory: Mintscan request failed (429 Too Many Requests) for /cosmoshub/cosmos/staking/v1beta1/validators/cosmosvaloper14jlpmqquh0gste6nzf4dn43kc8h50l6fmx6dfs/unbonding_delegations: ",
        "cosmosvaloper1kgquh04ffqvadekf6e47070gskm0s0h28cl7ht: All LCD providers failed for cosmos/staking/v1beta1/validators/cosmosvaloper1kgquh04ffqvadekf6e47070gskm0s0h28cl7ht/unbonding_delegations: cosmos.directory: Mintscan request failed (429 Too Many Requests) for /cosmoshub/cosmos/staking/v1beta1/validators/cosmosvaloper1kgquh04ffqvadekf6e47070gskm0s0h28cl7ht/unbonding_delegations: ",
        "cosmosvaloper1cjhz8st5409k2nzfcpcnexehjxh7k2fgn8kf3w: All LCD providers failed for cosmos/staking/v1beta1/validators/cosmosvaloper1cjhz8st5409k2nzfcpcnexehjxh7k2fgn8kf3w/unbonding_delegations: cosmos.directory: Mintscan request failed (429 Too Many Requests) for /cosmoshub/cosmos/staking/v1beta1/validators/cosmosvaloper1cjhz8st5409k2nzfcpcnexehjxh7k2fgn8kf3w/unbonding_delegations: "
      ],
      "windowDays": 45
    }
  }
}
